{"dokumente":{"@builddate":"20120625153031","@doknr":"BJNR200020991","norm":{"@builddate":"20120625153031","@doknr":"BJNR200020991","metadaten":{"jurabk":"AKP/EWGAbk4G","ausfertigung-datum":{"@manuell":"ja","#text":"1990-12-17"},"fundstelle":{"@typ":"amtlich","periodikum":"BGBl II","zitstelle":"1991, 2"},"langue":"Gesetz zu dem Vierten AKP-EWG-Abkommen von Lome vom\n15. Dezember 1989 sowie zu den mit diesem Abkommen in\nZusammenhang stehenden Abkommen"},"textdaten":{"text":{"@format":"decorated"}}}}}