{"dokumente":{"@builddate":"20120625152112","@doknr":"BJNR202620958","norm":{"@builddate":"20120625152112","@doknr":"BJNR202620958","metadaten":{"jurabk":"GrenzVtr BEL","ausfertigung-datum":{"@manuell":"ja","#text":"1956-09-24"},"fundstelle":{"@typ":"amtlich","periodikum":"BGBl II","zitstelle":"1958, 263"},"langue":"Vertrag zwischen der Bundesrepublik Deutschland und dem KÖnigreich\nBelgien über eine Berichtigung der deutsch-belgischen Grenze und andere die\nBeziehungen zwischen beiden Ländern betreffende Fragen"},"textdaten":{"text":{"@format":"decorated"},"fussnoten":{"Content":{"P":{"BR":null,"#text":"G v. 6.8.1958 II 262 Inkraft gem. Bek. v. 11.9.1958 II 353 mWv 28.8.1958"}}}}}}}