{"dokumente":{"@builddate":"20120625151713","@doknr":"BJNR206380952","norm":{"@builddate":"20120625151713","@doknr":"BJNR206380952","metadaten":{"jurabk":"IMFAbk","ausfertigung-datum":{"@manuell":"ja","#text":"1944-07-22"},"fundstelle":{"@typ":"amtlich","periodikum":"BGBl II","zitstelle":"1952, 638"},"langue":"Abkommen über den internationalen Währungsfonds"},"textdaten":{"text":{"@format":"decorated"},"fussnoten":{"Content":{"P":{"BR":null,"#text":"G v. 28.7.1952 II 637 In Kraft gem. Bek. v. 26.8.1952 II 728 mWv 14.8.1952"}}}}}}}