{"dokumente":{"@builddate":"20240630215118","@doknr":"BJNR0C20A0024","norm":[{"@builddate":"20240630215118","@doknr":"BJNR0C20A0024","metadaten":{"jurabk":"RWBestV 2024","amtabk":"RWBestV 2024","ausfertigung-datum":{"@manuell":"ja","#text":"2024-06-17"},"fundstelle":{"@typ":"amtlich","periodikum":"BGBl. I","zitstelle":"2024, Nr. 194"},"kurzue":"Rentenwertbestimmungsverordnung 2024","langue":"Verordnung zur Bestimmung des Rentenwerts in der gesetzlichen Rentenversicherung und zur Bestimmung weiterer Werte zum 1. Juli 2024"},"textdaten":{"fussnoten":{"Content":{"P":{"BR":null,"pre":{"@xml:space":"preserve","BR":[null,null],"#text":"(+++ Textnachweis ab: 1.7.2024 +++)"}}}}}},{"@builddate":"20240630215118","@doknr":"BJNR0C20A0024BJNE000100000","metadaten":{"jurabk":"RWBestV 2024","enbez":"Eingangsformel"},"textdaten":{"text":{"@format":"XML","Content":{"P":{"DL":{"@Type":"Dash","DT":["–","–","–"],"DD":[{"@Font":"normal","LA":"des § 69 Absatz 1 und des § 255f in Verbindung mit den §§ 68, 68a, 154 Absatz 3 und 3a, den §§ 228b, 255d Absatz 3 und den §§ 255e, 255h und 255i des Sechsten Buches Sozialgesetzbuch, von denen § 68 zuletzt durch Artikel 1 Nummer 2 des Gesetzes vom 28. Juni 2022 (BGBl. I S. 975), § 68a zuletzt durch Artikel 4 Nummer 3 des Gesetzes vom 15. Juli 2009 (BGBl. I S. 1939) und § 69 Absatz 1 zuletzt durch Artikel 4 Nummer 3 Buchstabe a des Gesetzes vom 22. Dezember 2011 (BGBl. I S. 3057) geändert worden sind, § 154 Absatz 3 durch Artikel 1 Nummer 8 Buchstabe a des Gesetzes vom 28. November 2018 (BGBl. I S. 2016) neu gefasst worden ist, § 154 Absatz 3a zuletzt durch Artikel 7 Nummer 2 des Gesetzes vom 19. Juni 2023 (BGBl. 2023 I Nr. 155) geändert worden ist, § 228b zuletzt durch Artikel 1 Nummer 11 des Gesetzes vom 17. Juli 2017 (BGBl. I S. 2575) geändert worden ist, § 255d Absatz 3 durch Artikel 1 Nummer 22 des Gesetzes vom 17. Juli 2017 (BGBl. I. S. 2575) neu gefasst worden ist, § 255e zuletzt durch Artikel 7 Nummer 3 des Gesetzes vom 19. Juni 2023 (BGBl. 2023 I Nr. 155) geändert worden ist, § 255f durch Artikel 1 Nummer 12 des Gesetzes vom 28. November 2018 (BGBl. I S. 2016) eingefügt worden ist und die §§ 255h und 255i durch Artikel 1 Nummer 7 des Gesetzes vom 28. Juni 2022 (BGBl. I S. 975) eingefügt worden sind,"},{"@Font":"normal","LA":"des § 26 in Verbindung mit § 23 Absatz 4 des Gesetzes über die Alterssicherung der Landwirte vom 29. Juli 1994 (BGBl. I S. 1890, 1891), das zuletzt durch Artikel 13 des Gesetzes vom 22. Dezember 2023 (BGBl. 2023 I Nr. 408) geändert worden ist und"},{"@Font":"normal","LA":"des § 44 Absatz 6 und des § 95 Absatz 1 Satz 2 des Siebten Buches Sozialgesetzbuch, von denen § 44 Absatz 6 durch Artikel 1 Nummer 2 Buchstabe b des Gesetzes vom 17. Juli 2001 (BGBl. I S. 1600) angefügt und § 95 Absatz 1 Satz 2 durch Artikel 4 Nummer 3 Buchstabe b des Gesetzes vom 21. Juli 2004 (BGBl. I S. 1791) geändert worden ist,"}]},"#text":"Auf Grund verordnet die Bundesregierung:"}}}}},{"@builddate":"20240630215118","@doknr":"BJNR0C20A0024BJNE000200000","metadaten":{"jurabk":"RWBestV 2024","enbez":"§ 1","titel":{"@format":"XML","#text":"Aktueller Rentenwert in der gesetzlichen Rentenversicherung"}},"textdaten":{"text":{"@format":"XML","Content":{"P":"Der aktuelle Rentenwert beträgt ab dem 1. Juli 2024 39,32 Euro."}}}},{"@builddate":"20240630215118","@doknr":"BJNR0C20A0024BJNE000300000","metadaten":{"jurabk":"RWBestV 2024","enbez":"§ 2","titel":{"@format":"XML","#text":"Ausgleichsbedarf in der gesetzlichen Rentenversicherung"}},"textdaten":{"text":{"@format":"XML","Content":{"P":"Der Ausgleichsbedarf beträgt ab dem 1. Juli 2024 1,0000."}}}},{"@builddate":"20240630215118","@doknr":"BJNR0C20A0024BJNE000400000","metadaten":{"jurabk":"RWBestV 2024","enbez":"§ 3","titel":{"@format":"XML","#text":"Sicherungsniveau vor Steuern in der gesetzlichen Rentenversicherung"}},"textdaten":{"text":{"@format":"XML","Content":{"P":"Das Sicherungsniveau vor Steuern beträgt für das Jahr 2024 48,00 Prozent."}}}},{"@builddate":"20240630215118","@doknr":"BJNR0C20A0024BJNE000500000","metadaten":{"jurabk":"RWBestV 2024","enbez":"§ 4","titel":{"@format":"XML","#text":"Allgemeiner Rentenwert in der Alterssicherung der Landwirte"}},"textdaten":{"text":{"@format":"XML","Content":{"P":"Der allgemeine Rentenwert in der Alterssicherung der Landwirte beträgt ab dem 1. Juli 2024 18,15 Euro."}}}},{"@builddate":"20240630215118","@doknr":"BJNR0C20A0024BJNE000600000","metadaten":{"jurabk":"RWBestV 2024","enbez":"§ 5","titel":{"@format":"XML","#text":"Anpassung der Geldleistungen in der gesetzlichen Unfallversicherung"}},"textdaten":{"text":{"@format":"XML","Content":{"P":["(1) Der Anpassungsfaktor für die zum 1. Juli 2024 anzupassenden Geldleistungen der gesetzlichen Unfallversicherung im Sinne des § 44 Absatz 4 und des § 95 des Siebten Buches Sozialgesetzbuch beträgt 1,0457.","(2) Das Pflegegeld der gesetzlichen Unfallversicherung beträgt ab dem 1. Juli 2024 für Versicherungsfälle, auf die § 44 Absatz 2 des Siebten Buches Sozialgesetzbuch anzuwenden ist, zwischen 445 Euro und 1 772 Euro monatlich."]}}}},{"@builddate":"20240630215118","@doknr":"BJNR0C20A0024BJNE000700000","metadaten":{"jurabk":"RWBestV 2024","enbez":"§ 6","titel":{"@format":"XML","#text":"Inkrafttreten"}},"textdaten":{"text":{"@format":"XML","Content":{"P":"Diese Verordnung tritt am 1. Juli 2024 in Kraft."}}}},{"@builddate":"20240630215118","@doknr":"BJNR0C20A0024BJNE000800000","metadaten":{"jurabk":"RWBestV 2024","enbez":"Schlussformel"},"textdaten":{"text":{"@format":"XML","Content":{"P":"Der Bundesrat hat zugestimmt."}}}}]}}