{"dokumente":{"@builddate":"20131008093614","@doknr":"BJNR030720998","norm":{"@builddate":"20131008093614","@doknr":"BJNR030720998","metadaten":{"jurabk":"SozSichAbk FIN 1997","ausfertigung-datum":{"@manuell":"ja","#text":"1997-04-28"},"fundstelle":{"@typ":"amtlich","periodikum":"BGBl II","zitstelle":"1998, 307"},"langue":"Abkommen zwischen der Bundesrepublik Deutschland\nund der Republik Finnland über Soziale Sicherheit"},"textdaten":{"text":{"@format":"decorated"},"fussnoten":{"Content":{"P":{"BR":null,"#text":"G v. 30.3.1998 II 306 In Kraft gem. Bek. v. 1.7.1998 II 1695 mWv 1.8.1998"}}}}}}}