{"dokumente":{"@builddate":"20160617215511","@doknr":"BJNR011220967","norm":[{"@builddate":"20160617215511","@doknr":"BJNR011220967","metadaten":{"jurabk":"WZG§4HUNBek","ausfertigung-datum":{"@manuell":"ja","#text":"1967-10-30"},"fundstelle":{"@typ":"amtlich","periodikum":"BGBl I","zitstelle":"1967, 1122"},"langue":"Bekanntmachung zu § 4 des Warenzeichengesetzes"},"textdaten":{"text":{"@format":"XML","Content":{"P":null}},"fussnoten":{"Content":{"P":"(+++ Textnachweis ab: 10.11.1967 +++)"}}}},{"@builddate":"20160617215511","@doknr":"BJNR011220967BJNE000100303","metadaten":{"jurabk":"WZG§4HUNBek","enbez":"(XXXX)"},"textdaten":{"text":{"@format":"XML","Content":{"P":["(1) Auf Grund des § 4 Abs. 2 Nr. 3 des Warenzeichengesetzes in der Fassung vom 9. Mai 1961 (Bundesgesetzbl. I S. 549, 574), zuletzt geändert durch Gesetz vom 4. September 1967 (Bundesgesetzbl. I S. 953), werden in der Anlage amtliche Prüf- und Gewährzeichen bekanntgemacht, die in der Volksrepublik Ungarn für Erzeugnisse aus Edelmetallen eingeführt sind.","(2) Diese Bekanntmachung ergeht im Anschluß an die Bekanntmachung vom 17. Mai 1967 (Bundesgesetzblatt I S. 574)."]}}}},{"@builddate":"20160617215511","@doknr":"BJNR011220967BJNE000900303","metadaten":{"jurabk":"WZG§4HUNBek","enbez":"Schlussformel"},"textdaten":{"text":{"@format":"XML","Content":{"P":"Der Bundesminister der Justiz"}}}},{"@builddate":"20160617215511","@doknr":"BJNR011220967BJNE000200303","metadaten":{"jurabk":"WZG§4HUNBek","enbez":"Anlage","titel":{"@format":"XML","#text":"Ungarische Prüf- und Gewährzeichen"}},"textdaten":{"text":{"@format":"XML","Content":{"P":{"noindex":{"kommentar":{"@typ":"Fundstelle","#text":"(Fundstelle: BGBl. I 1967, 1123 - 1124)"}},"IMG":[{"@Align":"center","@Pos":"block","@SRC":"bgbl1_1967_j1123_0010.jpg"},{"@Align":"center","@Pos":"block","@SRC":"bgbl1_1967_j1124_0010.jpg"}],"BR":[null,null]}}}}}]}}