{"dokumente":{"@builddate":"20131008093845","@doknr":"BJNR212300977","norm":{"@builddate":"20131008093845","@doknr":"BJNR212300977","metadaten":{"jurabk":"ZLuftSiÜbk","ausfertigung-datum":{"@manuell":"ja","#text":"1971-09-23"},"fundstelle":{"@typ":"amtlich","periodikum":"BGBl II","zitstelle":"1977, 1230"},"langue":"Übereinkommen zur Bekämpfung widerrechtlicher Handlungen gegen die\nSicherheit der Zivilluftfahrt"},"textdaten":{"text":{"@format":"decorated"},"fussnoten":{"Content":{"P":{"BR":null,"#text":"G v. 8.12.1977 II 1229 In Kraft gem. Bek. v. 6.3.1978 II 314 mWv 5.3.1978"}}}}}}}