{"dokumente":{"@builddate":"20120625150946","@doknr":"BJNR205770958","norm":{"@builddate":"20120625150946","@doknr":"BJNR205770958","metadaten":{"jurabk":"ZPÜbk Haag","ausfertigung-datum":{"@manuell":"ja","#text":"1954-03-01"},"fundstelle":{"@typ":"amtlich","periodikum":"BGBl II","zitstelle":"1958, 577"},"langue":"Übereinkommen über den Zivilprozeß"},"textdaten":{"text":{"@format":"decorated"},"fussnoten":{"Content":{"P":{"BR":null,"#text":"G v. 18.12.1958 II 576 In Kraft gem. Bek. v. 2.12.1959 II 1388 mWv 1.1.1960"}}}}}}}